LICENSE
README.md
setup.py
mygrader/__init__.py
mygrader/mygrader.py
mygrader/printer.py
mygrader/writer.py
mygrader.egg-info/PKG-INFO
mygrader.egg-info/SOURCES.txt
mygrader.egg-info/dependency_links.txt
mygrader.egg-info/entry_points.txt
mygrader.egg-info/requires.txt
mygrader.egg-info/top_level.txt
mygrader/src/__init__.py
mygrader/src/y2023.py
mygrader/template/__init__.py
mygrader/template/log_template.py
tests/test_mygrader.py