Metadata-Version: 2.1
Name: mygrader
Version: 0.44
Summary: my own CS111 grader.
Home-page: https://github.com/AppleBoiy/my-grader
Author: AppleBoiy
Author-email: contact.chaipat@gmail.com
Classifier: Development Status :: 3 - Alpha
Classifier: Intended Audience :: Developers
Classifier: License :: OSI Approved :: MIT License
Classifier: Programming Language :: Python :: 3
Classifier: Programming Language :: Python :: 3.8
Classifier: Programming Language :: Python :: 3.9
Classifier: Programming Language :: Python :: 3.10
Classifier: Programming Language :: Python :: 3.11
Provides-Extra: tests
License-File: LICENSE
